tutorial_pip_install_ry/__init__.py
tutorial_pip_install_ry/data.py
tutorial_pip_install_ry/inference.py
tutorial_pip_install_ry/model.py
tutorial_pip_install_ry/pretrained.py
tutorial_pip_install_ry/train.py
tutorial_pip_install_ry-0.1.0.dist-info/METADATA
tutorial_pip_install_ry-0.1.0.dist-info/WHEEL
tutorial_pip_install_ry-0.1.0.dist-info/top_level.txt
tutorial_pip_install_ry-0.1.0.dist-info/RECORD
