Metadata-Version: 2.4
Name: tutorial_pip_install_ry
Version: 0.1.0
Summary: Tutorial example: Keras MLP with Hugging Face-hosted data and model
Home-page: https://huggingface.co/RunyaoYu
Author: Runyao Yu
Author-email: runyao.yu@tudelft.nl
License: MIT
Requires-Python: >=3.8
Requires-Dist: tensorflow>=2.12
Requires-Dist: scikit-learn>=1.0
Requires-Dist: numpy>=1.22
Requires-Dist: pandas>=1.3
Requires-Dist: huggingface_hub>=0.20.0
Dynamic: author
Dynamic: author-email
Dynamic: home-page
Dynamic: license
Dynamic: requires-dist
Dynamic: requires-python
Dynamic: summary
